README.rst
setup.py
Clor.egg-info/PKG-INFO
Clor.egg-info/SOURCES.txt
Clor.egg-info/dependency_links.txt
Clor.egg-info/top_level.txt
clor/__init__.py
clor/test.py