Metadata-Version: 2.1
Name: Clor
Version: 0.4.0
Summary: Application configuration via Python logging.config
Home-page: https://heptapod.host/saajns/clor
Author: saaj
Author-email: mail@saaj.me
License: LGPL-2.1+
Project-URL: Source Code, https://heptapod.host/saajns/clor
Project-URL: Release Notes, https://heptapod.host/saajns/clor/-/blob/branch/default/HISTORY.rst
Keywords: python configuration-management
Platform: Any
Classifier: Topic :: Software Development :: Libraries
Classifier: Programming Language :: Python :: 3
Classifier: Programming Language :: Python :: 3 :: Only
Classifier: Programming Language :: Python :: 3.7
Classifier: Programming Language :: Python :: 3.8
Classifier: Programming Language :: Python :: 3.9
Classifier: Programming Language :: Python :: 3.10
Classifier: Programming Language :: Python :: Implementation :: CPython
Classifier: Intended Audience :: Developers
